wcraas_control/__init__.py
wcraas_control/cli.py
wcraas_control/config.py
wcraas_control/wcraas_control.py
wcraas_control-0.1.2.dist-info/AUTHORS.rst
wcraas_control-0.1.2.dist-info/LICENSE
wcraas_control-0.1.2.dist-info/METADATA
wcraas_control-0.1.2.dist-info/WHEEL
wcraas_control-0.1.2.dist-info/entry_points.txt
wcraas_control-0.1.2.dist-info/top_level.txt
wcraas_control-0.1.2.dist-info/RECORD
