Metadata-Version: 2.1
Name: wcraas-control
Version: 0.1.2
Summary: WCraaS Storage Service
Home-page: https://github.com/WCraaS/wcraas_control
Author: Kolokotronis Panagiotis
Author-email: panagiks@gmail.com
License: MIT license
Keywords: wcraas_control
Platform: UNKNOWN
Classifier: Development Status :: 2 - Pre-Alpha
Classifier: Intended Audience :: Developers
Classifier: License :: OSI Approved :: MIT License
Classifier: Natural Language :: English
Classifier: Programming Language :: Python :: 3
Classifier: Programming Language :: Python :: 3.6
Classifier: Programming Language :: Python :: 3.7
Requires-Python: >=3.6
Requires-Dist: aio-pika
Requires-Dist: aioredis
Requires-Dist: Click (>=7.0)
Requires-Dist: environs
Requires-Dist: wcraas-common
Requires-Dist: yarl (>=1.3.0)
